{
    "translations": {
        "de": {
            "VPN": "VPN",
            "Connected!": "Verbunden!",
            "Status": "Status",
            "Missing AuthKey!": "AuthKey fehlt!",
            "Fix": "Korrigieren",
            "The currently downloaded version seems broken!": "Die aktuell heruntergeladene Version scheint defekt!",
            "Update": "Aktualisieren",
            "Version": "Version",
            "Service": "Dienst",
            "Running!": "Läuft!",
            "Stopped!": "Gestoppt!",
            "Tunnel": "Tunnel",
            "Start Tunnel": "Tunnel starten",
            "Start Service": "Dienst starten",
            "Download": "Herunterladen",
            "Auth Key": "Auth Key",
            "Stopping Tunnel...": "Stoppe Tunnel...",
            "Stopping Service...": "Stoppe Dienst...",
            "Downloading...": "Herunterladen...",
            "Download failed!": "Herunterladen fehlgeschlagen!",
            "Hash validation failed!": "Hash-Validierung fehlgeschlagen!",
            "Extracting...": "Entpacken...",
            "Cleanup...": "Aufräumen...",
            "Starting Service...": "Starte Dienst...",
            "Starting Tunnel...": "Starte Tunnel...",
            "Please wait...": "Bitte Warten...",
            "Tailscale is not yet installed": "Tailscale ist noch nicht installiert",
            "Tailscale is not yet authenticated": "Tailscale ist noch nicht authentifiziert",
            "Authenticate": "Authentifizieren",
            "Authenticate with Tailscale": "Mit Tailscale authentifizieren",
            "Tailscale VPN is only available for SymBox!": "Tailscale VPN ist nur für die SymBox verfügbar!",
            "Not installed!": "Nicht installiert!",
            "Activate VPN on startup": "VPN beim Starten automatisch aktivieren",
            "Reset completely": "Komplett zurücksetzen",
            "Do you really want to remove Tailscale completely with all associated data?": "Wollen Sie Tailscale wirklich komplett mit allen zugehörigen Daten entfernen?",
            "Not enough temporary disk space. Please reboot SymBox and try again!": "Nicht genügend temporärer Speicherplatz. Bitte starten Sie SymBox neu und versuchen Sie es erneut!"
        }
    }
}